pytups/__init__.py
pytups/orderedSet.py
pytups/superdict.py
pytups/tools.py
pytups/tuplist.py
pytups-1.0.4.dist-info/licenses/AUTHORS.md
pytups-1.0.4.dist-info/licenses/LICENSE.txt
pytups-1.0.4.dist-info/METADATA
pytups-1.0.4.dist-info/WHEEL
pytups-1.0.4.dist-info/top_level.txt
pytups-1.0.4.dist-info/RECORD
