Metadata-Version: 2.4
Name: pytups
Version: 1.0.4
Summary: data wrangling for lists of tuples and dictionaries
Author-email: Franco Peschiera <pchtsp@gmail.com>
Maintainer-email: Franco Peschiera <pchtsp@gmail.com>
Project-URL: source, https://github.com/pchtsp/pytups
Project-URL: download, https://github.com/pchtsp/pytups/archive/master.zip
Keywords: super dict,dictionary,tuple list,math,pulp
Classifier: Programming Language :: Python :: 3
Classifier: Operating System :: OS Independent
Requires-Python: >=3.9
License-File: LICENSE.txt
License-File: AUTHORS.md
Dynamic: license-file
